{"name":"深度学习","slug":"深度学习","count":4,"postlist":[{"title":"注意力机制","uid":"355624fb0490d5f1612ed79605ab0b34","slug":"attention","date":"2024-09-22T05:51:09.000Z","updated":"2024-09-29T06:07:49.129Z","comments":true,"path":"api/articles/attention.json","keywords":null,"cover":[],"text":"Attention自注意力机制Self-attention注意力机制在设计之初的目标是接收一段文本，预测其下一个词。 首先，输入文本会被切分成小块，称之为tok...","permalink":"/post/attention","photos":[],"count_time":{"symbolsCount":"2k","symbolsTime":"2 mins."},"categories":[{"name":"深度学习","slug":"深度学习","count":4,"path":"api/categories/深度学习.json"}],"tags":[{"name":"attention","slug":"attention","count":1,"path":"api/tags/attention.json"},{"name":"transformer","slug":"transformer","count":1,"path":"api/tags/transformer.json"}],"author":{"name":"Sonderlin","slug":"blog-author","avatar":"https://raw.githubusercontent.com/sonder-lin/Mypic/img/img/%E5%A4%B4%E5%83%8F.jpg","link":"/","description":"一位正在重塑知识的小蒟蒻~ <br /> <b><i>过了河便是繁星。</i></b> <br /><br /> @ <b>qq：1425906813</b>","socials":{"github":"","twitter":"","stackoverflow":"","wechat":"","qq":"","weibo":"","zhihu":"","csdn":"","juejin":"","customs":{}}}},{"title":"Stable Diffusion","uid":"9f952bd90e9edabc954e41df6aae978e","slug":"Stable-Diffusion","date":"2024-09-22T05:51:09.000Z","updated":"2025-01-05T10:53:26.530Z","comments":true,"path":"api/articles/Stable-Diffusion.json","keywords":null,"cover":[],"text":"Stable DiffusionStable Diffusion 本身并不是一个模型，而是一个由多个模块和模型组成的系统架构，它由三大核心部件组成，每个组件都是...","permalink":"/post/Stable-Diffusion","photos":[],"count_time":{"symbolsCount":508,"symbolsTime":"1 mins."},"categories":[{"name":"深度学习","slug":"深度学习","count":4,"path":"api/categories/深度学习.json"}],"tags":[{"name":"SD扩散模型","slug":"SD扩散模型","count":1,"path":"api/tags/SD扩散模型.json"},{"name":"AIGC","slug":"AIGC","count":2,"path":"api/tags/AIGC.json"}],"author":{"name":"Sonderlin","slug":"blog-author","avatar":"https://raw.githubusercontent.com/sonder-lin/Mypic/img/img/%E5%A4%B4%E5%83%8F.jpg","link":"/","description":"一位正在重塑知识的小蒟蒻~ <br /> <b><i>过了河便是繁星。</i></b> <br /><br /> @ <b>qq：1425906813</b>","socials":{"github":"","twitter":"","stackoverflow":"","wechat":"","qq":"","weibo":"","zhihu":"","csdn":"","juejin":"","customs":{}}}},{"title":"Diffusion Model","uid":"7ce7aaea6148fcaf3be1f2eb31902870","slug":"diffusion model","date":"2024-09-21T05:51:09.000Z","updated":"2025-01-05T10:53:43.913Z","comments":true,"path":"api/articles/diffusion model.json","keywords":null,"cover":[],"text":"Diffusion Model原理解析前向扩散过程前向扩散过程本质上为一个对原始图片输入逐步加噪的过程，公式如下所示：其中，表示在时刻的噪音，其服从正态分布：....","permalink":"/post/diffusion model","photos":[],"count_time":{"symbolsCount":632,"symbolsTime":"1 mins."},"categories":[{"name":"深度学习","slug":"深度学习","count":4,"path":"api/categories/深度学习.json"}],"tags":[{"name":"AIGC","slug":"AIGC","count":2,"path":"api/tags/AIGC.json"},{"name":"扩散模型","slug":"扩散模型","count":1,"path":"api/tags/扩散模型.json"}],"author":{"name":"Sonderlin","slug":"blog-author","avatar":"https://raw.githubusercontent.com/sonder-lin/Mypic/img/img/%E5%A4%B4%E5%83%8F.jpg","link":"/","description":"一位正在重塑知识的小蒟蒻~ <br /> <b><i>过了河便是繁星。</i></b> <br /><br /> @ <b>qq：1425906813</b>","socials":{"github":"","twitter":"","stackoverflow":"","wechat":"","qq":"","weibo":"","zhihu":"","csdn":"","juejin":"","customs":{}}}},{"title":"深度学习","uid":"cc42225e358de83b2373cd0847dd2b15","slug":"深度学习","date":"2024-01-31T05:51:09.000Z","updated":"2024-11-08T08:32:15.277Z","comments":true,"path":"api/articles/深度学习.json","keywords":null,"cover":[],"text":"深度学习数据操作tensor为torch中的一个数据结构，可以参与运算，称为张量，即多个数值组成的数组，可能有多个维度 pythonimport torch x...","permalink":"/post/深度学习","photos":[],"count_time":{"symbolsCount":"13k","symbolsTime":"12 mins."},"categories":[{"name":"深度学习","slug":"深度学习","count":4,"path":"api/categories/深度学习.json"}],"tags":[{"name":"Pytorch","slug":"Pytorch","count":1,"path":"api/tags/Pytorch.json"}],"author":{"name":"Sonderlin","slug":"blog-author","avatar":"https://raw.githubusercontent.com/sonder-lin/Mypic/img/img/%E5%A4%B4%E5%83%8F.jpg","link":"/","description":"一位正在重塑知识的小蒟蒻~ <br /> <b><i>过了河便是繁星。</i></b> <br /><br /> @ <b>qq：1425906813</b>","socials":{"github":"","twitter":"","stackoverflow":"","wechat":"","qq":"","weibo":"","zhihu":"","csdn":"","juejin":"","customs":{}}}}]}